dikshantnetvoice/__init__.py
dikshantnetvoice/commands.py
dikshantnetvoice/utils.py
dikshantnetvoice/voice_engine.py
dikshantnetvoice/data/commands.json
dikshantnetvoice/data/model/README
dikshantnetvoice/data/model/am/final.mdl
dikshantnetvoice/data/model/conf/mfcc.conf
dikshantnetvoice/data/model/conf/model.conf
dikshantnetvoice/data/model/graph/Gr.fst
dikshantnetvoice/data/model/graph/HCLr.fst
dikshantnetvoice/data/model/graph/disambig_tid.int
dikshantnetvoice/data/model/graph/phones/word_boundary.int
dikshantnetvoice/data/model/ivector/final.dubm
dikshantnetvoice/data/model/ivector/final.ie
dikshantnetvoice/data/model/ivector/final.mat
dikshantnetvoice/data/model/ivector/global_cmvn.stats
dikshantnetvoice/data/model/ivector/online_cmvn.conf
dikshantnetvoice/data/model/ivector/splice.conf
dikshantnetvoice-0.2.5.dist-info/licenses/LICENSE.txt
dikshantnetvoice-0.2.5.dist-info/METADATA
dikshantnetvoice-0.2.5.dist-info/WHEEL
dikshantnetvoice-0.2.5.dist-info/top_level.txt
dikshantnetvoice-0.2.5.dist-info/RECORD
