Metadata-Version: 2.4
Name: dikshantnetvoice
Version: 0.2.5
Summary: Offline voice-controlled networking toolkit
Author-email: Dikshant Ghimire <dikkughimire@email.com>
Project-URL: Homepage, https://github.com/dikshantgh/dikshantnetvoice
Requires-Python: >=3.7
License-File: LICENSE.txt
Requires-Dist: vosk
Requires-Dist: pyaudio
Requires-Dist: netifaces
Requires-Dist: python-nmap
Provides-Extra: windows
Requires-Dist: pywin32; extra == "windows"
Provides-Extra: linux
Requires-Dist: networkmanager; extra == "linux"
Dynamic: license-file
